[
  {
    "name": "Dave Meng",
    "leaveDate": "2026-01-19"
  },
  {
    "name": "Dave Meng",
    "leaveDate": "2026-01-20"
  },
  {
    "name": "Dave Meng",
    "leaveDate": "2026-01-21"
  },
  {
    "name": "Dave Meng",
    "leaveDate": "2026-01-22"
  },
  {
    "name": "Dave Meng",
    "leaveDate": "2026-01-23"
  },
  {
    "name": "Dave Meng",
    "leaveDate": "2026-01-26"
  },
  {
    "name": "Dave Meng",
    "leaveDate": "2026-01-27"
  },
  {
    "name": "Dave Meng",
    "leaveDate": "2026-01-28"
  },
  {
    "name": "Dave Meng",
    "leaveDate": "2026-01-29"
  },
  {
    "name": "Dave Meng",
    "leaveDate": "2026-01-30"
  },
  {
    "name": "DK Xiong",
    "leaveDate": "2026-01-02"
  },
  {
    "name": "Iron Xia",
    "leaveDate": "2026-01-02",
    "part": "am"
  },
  {
    "name": "Iron Xia",
    "leaveDate": "2026-01-12",
    "part": "am"
  },
  {
    "name": "Jim Hu",
    "leaveDate": "2026-01-02"
  },
  {
    "name": "Layne Wang",
    "leaveDate": "2026-01-08"
  },
  {
    "name": "Layne Wang",
    "leaveDate": "2026-01-21"
  },
  {
    "name": "Layne Wang",
    "leaveDate": "2026-01-23"
  },
  {
    "name": "Layne Wang",
    "leaveDate": "2026-01-30",
    "part": "am"
  },
  {
    "name": "Lex Xiao",
    "leaveDate": "2026-01-02"
  },
  {
    "name": "Luffy Ji",
    "leaveDate": "2026-01-02"
  },
  {
    "name": "Luffy Ji",
    "leaveDate": "2026-01-05"
  },
  {
    "name": "Luffy Ji",
    "leaveDate": "2026-01-06"
  },
  {
    "name": "Luffy Ji",
    "leaveDate": "2026-01-07"
  },
  {
    "name": "Luffy Ji",
    "leaveDate": "2026-01-08"
  },
  {
    "name": "Luffy Ji",
    "leaveDate": "2026-01-09"
  },
  {
    "name": "Luffy Ji",
    "leaveDate": "2026-01-12"
  },
  {
    "name": "Luffy Ji",
    "leaveDate": "2026-01-13"
  },
  {
    "name": "Luffy Ji",
    "leaveDate": "2026-01-14"
  },
  {
    "name": "Luffy Ji",
    "leaveDate": "2026-01-15"
  },
  {
    "name": "Luffy Ji",
    "leaveDate": "2026-01-16"
  },
  {
    "name": "Luffy Ji",
    "leaveDate": "2026-01-19"
  },
  {
    "name": "Luffy Ji",
    "leaveDate": "2026-01-20"
  },
  {
    "name": "Luffy Ji",
    "leaveDate": "2026-01-21"
  },
  {
    "name": "Luffy Ji",
    "leaveDate": "2026-01-22"
  },
  {
    "name": "Luffy Ji",
    "leaveDate": "2026-01-23"
  },
  {
    "name": "Luffy Ji",
    "leaveDate": "2026-01-26"
  },
  {
    "name": "Luffy Ji",
    "leaveDate": "2026-01-27"
  },
  {
    "name": "Luffy Ji",
    "leaveDate": "2026-01-28"
  },
  {
    "name": "Luffy Ji",
    "leaveDate": "2026-01-29"
  },
  {
    "name": "Luffy Ji",
    "leaveDate": "2026-01-30"
  },
  {
    "name": "Mark Ma",
    "leaveDate": "2026-01-02"
  },
  {
    "name": "Monster Wang",
    "leaveDate": "2026-01-13"
  },
  {
    "name": "Oliver Dong",
    "leaveDate": "2026-01-02"
  },
  {
    "name": "Peter Li",
    "leaveDate": "2026-01-21"
  },
  {
    "name": "Rain Gu",
    "leaveDate": "2026-01-23"
  },
  {
    "name": "Tony Zhong",
    "leaveDate": "2026-01-06"
  },
  {
    "name": "Alex Yang",
    "leaveDate": "2026-02-11"
  },
  {
    "name": "Allen Qiao",
    "leaveDate": "2026-02-12"
  },
  {
    "name": "Allen Qiao",
    "leaveDate": "2026-02-20"
  },
  {
    "name": "Allen Qiao",
    "leaveDate": "2026-02-23"
  },
  {
    "name": "Dave Meng",
    "leaveDate": "2026-02-01"
  },
  {
    "name": "Dave Meng",
    "leaveDate": "2026-02-02"
  },
  {
    "name": "Dave Meng",
    "leaveDate": "2026-02-03"
  },
  {
    "name": "Dave Meng",
    "leaveDate": "2026-02-04"
  },
  {
    "name": "Dave Meng",
    "leaveDate": "2026-02-05"
  },
  {
    "name": "Dave Meng",
    "leaveDate": "2026-02-06"
  },
  {
    "name": "Dave Meng",
    "leaveDate": "2026-02-09"
  },
  {
    "name": "Dave Meng",
    "leaveDate": "2026-02-10"
  },
  {
    "name": "Dave Meng",
    "leaveDate": "2026-02-11"
  },
  {
    "name": "Dave Meng",
    "leaveDate": "2026-02-12"
  },
  {
    "name": "Dave Meng",
    "leaveDate": "2026-02-13"
  },
  {
    "name": "Dave Meng",
    "leaveDate": "2026-02-20"
  },
  {
    "name": "DK Xiong",
    "leaveDate": "2026-02-11"
  },
  {
    "name": "DK Xiong",
    "leaveDate": "2026-02-12"
  },
  {
    "name": "DK Xiong",
    "leaveDate": "2026-02-13"
  },
  {
    "name": "DK Xiong",
    "leaveDate": "2026-02-20"
  },
  {
    "name": "DK Xiong",
    "leaveDate": "2026-02-25"
  },
  {
    "name": "DK Xiong",
    "leaveDate": "2026-02-26"
  },
  {
    "name": "DK Xiong",
    "leaveDate": "2026-02-27"
  },
  {
    "name": "Dylan Xie",
    "leaveDate": "2026-02-09",
    "part": "am"
  },
  {
    "name": "Dylan Xie",
    "leaveDate": "2026-02-10"
  },
  {
    "name": "Dylan Xie",
    "leaveDate": "2026-02-11"
  },
  {
    "name": "Dylan Xie",
    "leaveDate": "2026-02-12"
  },
  {
    "name": "Dylan Xie",
    "leaveDate": "2026-02-13"
  },
  {
    "name": "Hans Xiao",
    "leaveDate": "2026-02-12"
  },
  {
    "name": "Hans Xiao",
    "leaveDate": "2026-02-13"
  },
  {
    "name": "Hans Xiao",
    "leaveDate": "2026-02-20"
  },
  {
    "name": "Iron Xia",
    "leaveDate": "2026-02-13"
  },
  {
    "name": "Iron Xia",
    "leaveDate": "2026-02-23"
  },
  {
    "name": "Iron Xia",
    "leaveDate": "2026-02-24"
  },
  {
    "name": "Iron Xia",
    "leaveDate": "2026-02-25"
  },
  {
    "name": "Jim Hu",
    "leaveDate": "2026-02-09"
  },
  {
    "name": "Jim Hu",
    "leaveDate": "2026-02-10"
  },
  {
    "name": "Jim Hu",
    "leaveDate": "2026-02-11"
  },
  {
    "name": "Jim Hu",
    "leaveDate": "2026-02-12"
  },
  {
    "name": "Jim Hu",
    "leaveDate": "2026-02-13"
  },
  {
    "name": "Layne Wang",
    "leaveDate": "2026-02-24"
  },
  {
    "name": "Layne Wang",
    "leaveDate": "2026-02-25"
  },
  {
    "name": "Lex Xiao",
    "leaveDate": "2026-02-13"
  },
  {
    "name": "Lex Xiao",
    "leaveDate": "2026-02-20"
  },
  {
    "name": "Louis Meng",
    "leaveDate": "2026-02-13"
  },
  {
    "name": "Louis Meng",
    "leaveDate": "2026-02-20"
  },
  {
    "name": "Luffy Ji",
    "leaveDate": "2026-02-01"
  },
  {
    "name": "Luffy Ji",
    "leaveDate": "2026-02-02"
  },
  {
    "name": "Luffy Ji",
    "leaveDate": "2026-02-03"
  },
  {
    "name": "Luffy Ji",
    "leaveDate": "2026-02-04"
  },
  {
    "name": "Luffy Ji",
    "leaveDate": "2026-02-05"
  },
  {
    "name": "Luffy Ji",
    "leaveDate": "2026-02-06"
  },
  {
    "name": "Luffy Ji",
    "leaveDate": "2026-02-09"
  },
  {
    "name": "Luffy Ji",
    "leaveDate": "2026-02-10"
  },
  {
    "name": "Luffy Ji",
    "leaveDate": "2026-02-11"
  },
  {
    "name": "Luffy Ji",
    "leaveDate": "2026-02-12"
  },
  {
    "name": "Luffy Ji",
    "leaveDate": "2026-02-13"
  },
  {
    "name": "Luffy Ji",
    "leaveDate": "2026-02-20"
  },
  {
    "name": "Luffy Ji",
    "leaveDate": "2026-02-23"
  },
  {
    "name": "Luffy Ji",
    "leaveDate": "2026-02-24"
  },
  {
    "name": "Luffy Ji",
    "leaveDate": "2026-02-25"
  },
  {
    "name": "Luffy Ji",
    "leaveDate": "2026-02-26"
  },
  {
    "name": "Luffy Ji",
    "leaveDate": "2026-02-27"
  },
  {
    "name": "Mark Ma",
    "leaveDate": "2026-02-03"
  },
  {
    "name": "Mark Ma",
    "leaveDate": "2026-02-04"
  },
  {
    "name": "Mark Ma",
    "leaveDate": "2026-02-05"
  },
  {
    "name": "Mark Ma",
    "leaveDate": "2026-02-20"
  },
  {
    "name": "Max Chen",
    "leaveDate": "2026-02-09",
    "part": "pm"
  },
  {
    "name": "Max Chen",
    "leaveDate": "2026-02-20"
  },
  {
    "name": "Monster Wang",
    "leaveDate": "2026-02-20"
  },
  {
    "name": "Monster Wang",
    "leaveDate": "2026-02-27"
  },
  {
    "name": "Nevin Li",
    "leaveDate": "2026-02-20"
  },
  {
    "name": "Oliver Dong",
    "leaveDate": "2026-02-20"
  },
  {
    "name": "Parry Pan",
    "leaveDate": "2026-02-12"
  },
  {
    "name": "Parry Pan",
    "leaveDate": "2026-02-13"
  },
  {
    "name": "Parry Pan",
    "leaveDate": "2026-02-20"
  },
  {
    "name": "Parry Pan",
    "leaveDate": "2026-02-23"
  },
  {
    "name": "Peter Li",
    "leaveDate": "2026-02-20"
  },
  {
    "name": "Peter Li",
    "leaveDate": "2026-02-23"
  },
  {
    "name": "Rain Gu",
    "leaveDate": "2026-02-20"
  },
  {
    "name": "Vae Wang",
    "leaveDate": "2026-02-13"
  },
  {
    "name": "Vae Wang",
    "leaveDate": "2026-02-20"
  },
  {
    "name": "Vae Wang",
    "leaveDate": "2026-02-23"
  },
  {
    "name": "Zick Ling",
    "leaveDate": "2026-02-11"
  },
  {
    "name": "Zick Ling",
    "leaveDate": "2026-02-12"
  },
  {
    "name": "Zick Ling",
    "leaveDate": "2026-02-13"
  },
  {
    "name": "Zick Ling",
    "leaveDate": "2026-02-20"
  },
  {
    "name": "Iris Li",
    "leaveDate": "2026-02-20"
  },
  {
    "name": "Allen Qiao",
    "leaveDate": "2026-03-09"
  },
  {
    "name": "Allen Qiao",
    "leaveDate": "2026-03-10"
  },
  {
    "name": "Allen Qiao",
    "leaveDate": "2026-03-30"
  },
  {
    "name": "DK Xiong",
    "leaveDate": "2026-03-04"
  },
  {
    "name": "Iron Xia",
    "leaveDate": "2026-03-10"
  },
  {
    "name": "Louis Meng",
    "leaveDate": "2026-03-02"
  },
  {
    "name": "Louis Meng",
    "leaveDate": "2026-03-03"
  },
  {
    "name": "Monster Wang",
    "leaveDate": "2026-03-03"
  },
  {
    "name": "Monster Wang",
    "leaveDate": "2026-03-20"
  },
  {
    "name": "Reese Li",
    "leaveDate": "2026-03-31"
  },
  {
    "name": "Allen Qiao",
    "leaveDate": "2026-04-03"
  },
  {
    "name": "Dylan Xie",
    "leaveDate": "2026-04-03"
  },
  {
    "name": "Hans Xiao",
    "leaveDate": "2026-04-02"
  },
  {
    "name": "Hans Xiao",
    "leaveDate": "2026-04-03"
  },
  {
    "name": "Jim Hu",
    "leaveDate": "2026-04-07"
  },
  {
    "name": "Jim Hu",
    "leaveDate": "2026-04-08"
  },
  {
    "name": "Layne Wang",
    "leaveDate": "2026-04-15"
  },
  {
    "name": "Louis Meng",
    "leaveDate": "2026-04-07"
  },
  {
    "name": "Mark Ma",
    "leaveDate": "2026-04-01"
  },
  {
    "name": "Mark Ma",
    "leaveDate": "2026-04-02"
  },
  {
    "name": "Monster Wang",
    "leaveDate": "2026-04-07"
  },
  {
    "name": "Monster Wang",
    "leaveDate": "2026-04-14"
  },
  {
    "name": "Peter Li",
    "leaveDate": "2026-04-30"
  },
  {
    "name": "Rain Gu",
    "leaveDate": "2026-04-07"
  },
  {
    "name": "Vae Wang",
    "leaveDate": "2026-04-07"
  },
  {
    "name": "Zick Ling",
    "leaveDate": "2026-04-29"
  },
  {
    "name": "Zick Ling",
    "leaveDate": "2026-04-30"
  },
  {
    "name": "Alex Yang",
    "leaveDate": "2026-05-05"
  },
  {
    "name": "DK Xiong",
    "leaveDate": "2026-05-06"
  },
  {
    "name": "Iron Xia",
    "leaveDate": "2026-05-05"
  },
  {
    "name": "Layne Wang",
    "leaveDate": "2026-05-15"
  },
  {
    "name": "Louis Meng",
    "leaveDate": "2026-05-05"
  },
  {
    "name": "Mark Ma",
    "leaveDate": "2026-05-05"
  },
  {
    "name": "Max Chen",
    "leaveDate": "2026-05-05"
  },
  {
    "name": "Max Chen",
    "leaveDate": "2026-05-06"
  },
  {
    "name": "Monster Wang",
    "leaveDate": "2026-05-05"
  },
  {
    "name": "Monster Wang",
    "leaveDate": "2026-05-26"
  },
  {
    "name": "Peter Li",
    "leaveDate": "2026-05-05"
  },
  {
    "name": "Peter Li",
    "leaveDate": "2026-05-29"
  },
  {
    "name": "Rain Gu",
    "leaveDate": "2026-05-05"
  },
  {
    "name": "Allen Qiao",
    "leaveDate": "2026-06-01"
  },
  {
    "name": "Allen Qiao",
    "leaveDate": "2026-06-18"
  },
  {
    "name": "DK Xiong",
    "leaveDate": "2026-06-03"
  },
  {
    "name": "Dylan Xie",
    "leaveDate": "2026-06-22"
  },
  {
    "name": "Dylan Xie",
    "leaveDate": "2026-06-23"
  },
  {
    "name": "Dylan Xie",
    "leaveDate": "2026-06-24"
  },
  {
    "name": "Dylan Xie",
    "leaveDate": "2026-06-25"
  },
  {
    "name": "Dylan Xie",
    "leaveDate": "2026-06-26"
  },
  {
    "name": "Jim Hu",
    "leaveDate": "2026-06-01"
  },
  {
    "name": "Layne Wang",
    "leaveDate": "2026-06-15"
  },
  {
    "name": "Louis Meng",
    "leaveDate": "2026-06-01"
  },
  {
    "name": "Louis Meng",
    "leaveDate": "2026-06-02"
  },
  {
    "name": "Peter Li",
    "leaveDate": "2026-06-18"
  },
  {
    "name": "Rain Gu",
    "leaveDate": "2026-06-15"
  },
  {
    "name": "Rain Gu",
    "leaveDate": "2026-06-16"
  },
  {
    "name": "Rain Gu",
    "leaveDate": "2026-06-22"
  },
  {
    "name": "Rain Gu",
    "leaveDate": "2026-06-23"
  },
  {
    "name": "Rain Gu",
    "leaveDate": "2026-06-24"
  },
  {
    "name": "Reese Li",
    "leaveDate": "2026-06-01"
  },
  {
    "name": "Allen Qiao",
    "leaveDate": "2026-07-13"
  },
  {
    "name": "DK Xiong",
    "leaveDate": "2026-07-01"
  },
  {
    "name": "Dylan Xie",
    "leaveDate": "2026-07-13"
  },
  {
    "name": "Dylan Xie",
    "leaveDate": "2026-07-14"
  },
  {
    "name": "Iron Xia",
    "leaveDate": "2026-07-13"
  },
  {
    "name": "Layne Wang",
    "leaveDate": "2026-07-15"
  },
  {
    "name": "Louis Meng",
    "leaveDate": "2026-07-06"
  },
  {
    "name": "Louis Meng",
    "leaveDate": "2026-07-07"
  },
  {
    "name": "Mark Ma",
    "leaveDate": "2026-07-01"
  },
  {
    "name": "Mark Ma",
    "leaveDate": "2026-07-02"
  },
  {
    "name": "Max Chen",
    "leaveDate": "2026-07-23"
  },
  {
    "name": "Max Chen",
    "leaveDate": "2026-07-24"
  },
  {
    "name": "Monster Wang",
    "leaveDate": "2026-07-14"
  },
  {
    "name": "Monster Wang",
    "leaveDate": "2026-07-15"
  },
  {
    "name": "Oliver Dong",
    "leaveDate": "2026-07-20"
  },
  {
    "name": "Oliver Dong",
    "leaveDate": "2026-07-21"
  },
  {
    "name": "Oliver Dong",
    "leaveDate": "2026-07-22"
  },
  {
    "name": "Oliver Dong",
    "leaveDate": "2026-07-23"
  },
  {
    "name": "Parry Pan",
    "leaveDate": "2026-07-15"
  },
  {
    "name": "Peter Li",
    "leaveDate": "2026-07-06"
  },
  {
    "name": "Peter Li",
    "leaveDate": "2026-07-07"
  },
  {
    "name": "Zick Ling",
    "leaveDate": "2026-07-20"
  },
  {
    "name": "Zick Ling",
    "leaveDate": "2026-07-21"
  },
  {
    "name": "Zick Ling",
    "leaveDate": "2026-07-22"
  },
  {
    "name": "Zick Ling",
    "leaveDate": "2026-07-23"
  },
  {
    "name": "Zick Ling",
    "leaveDate": "2026-07-24"
  },
  {
    "name": "Allen Qiao",
    "leaveDate": "2026-08-24"
  },
  {
    "name": "DK Xiong",
    "leaveDate": "2026-08-05"
  },
  {
    "name": "Dylan Xie",
    "leaveDate": "2026-08-17"
  },
  {
    "name": "Dylan Xie",
    "leaveDate": "2026-08-18"
  },
  {
    "name": "Iron Xia",
    "leaveDate": "2026-08-17"
  },
  {
    "name": "Jim Hu",
    "leaveDate": "2026-08-03"
  },
  {
    "name": "Jim Hu",
    "leaveDate": "2026-08-04"
  },
  {
    "name": "Jim Hu",
    "leaveDate": "2026-08-05"
  },
  {
    "name": "Jim Hu",
    "leaveDate": "2026-08-06"
  },
  {
    "name": "Jim Hu",
    "leaveDate": "2026-08-07"
  },
  {
    "name": "Monster Wang",
    "leaveDate": "2026-08-03"
  },
  {
    "name": "Monster Wang",
    "leaveDate": "2026-08-04"
  },
  {
    "name": "Monster Wang",
    "leaveDate": "2026-08-05"
  },
  {
    "name": "Peter Li",
    "leaveDate": "2026-08-03"
  },
  {
    "name": "Peter Li",
    "leaveDate": "2026-08-07"
  },
  {
    "name": "Reese Li",
    "leaveDate": "2026-08-31"
  },
  {
    "name": "DK Xiong",
    "leaveDate": "2026-09-02"
  },
  {
    "name": "Dylan Xie",
    "leaveDate": "2026-09-28"
  },
  {
    "name": "Dylan Xie",
    "leaveDate": "2026-09-29"
  },
  {
    "name": "Dylan Xie",
    "leaveDate": "2026-09-30"
  },
  {
    "name": "Layne Wang",
    "leaveDate": "2026-09-15"
  },
  {
    "name": "Lex Xiao",
    "leaveDate": "2026-09-28"
  },
  {
    "name": "Lex Xiao",
    "leaveDate": "2026-09-29"
  },
  {
    "name": "Lex Xiao",
    "leaveDate": "2026-09-30"
  },
  {
    "name": "Louis Meng",
    "leaveDate": "2026-09-07"
  },
  {
    "name": "Max Chen",
    "leaveDate": "2026-09-28"
  },
  {
    "name": "Max Chen",
    "leaveDate": "2026-09-29"
  },
  {
    "name": "Max Chen",
    "leaveDate": "2026-09-30"
  },
  {
    "name": "Monster Wang",
    "leaveDate": "2026-09-08"
  },
  {
    "name": "Nevin Li",
    "leaveDate": "2026-09-28"
  },
  {
    "name": "Nevin Li",
    "leaveDate": "2026-09-29"
  },
  {
    "name": "Nevin Li",
    "leaveDate": "2026-09-30"
  },
  {
    "name": "Rain Gu",
    "leaveDate": "2026-09-28"
  },
  {
    "name": "Rain Gu",
    "leaveDate": "2026-09-29"
  },
  {
    "name": "Rain Gu",
    "leaveDate": "2026-09-30"
  },
  {
    "name": "Alex Yang",
    "leaveDate": "2026-10-07"
  },
  {
    "name": "Alex Yang",
    "leaveDate": "2026-10-08"
  },
  {
    "name": "Alex Yang",
    "leaveDate": "2026-10-09"
  },
  {
    "name": "DK Xiong",
    "leaveDate": "2026-10-08"
  },
  {
    "name": "Iron Xia",
    "leaveDate": "2026-10-06"
  },
  {
    "name": "Iron Xia",
    "leaveDate": "2026-10-07"
  },
  {
    "name": "Jim Hu",
    "leaveDate": "2026-10-06"
  },
  {
    "name": "Jim Hu",
    "leaveDate": "2026-10-07"
  },
  {
    "name": "Jim Hu",
    "leaveDate": "2026-10-08"
  },
  {
    "name": "Jim Hu",
    "leaveDate": "2026-10-09"
  },
  {
    "name": "Layne Wang",
    "leaveDate": "2026-10-15"
  },
  {
    "name": "Louis Meng",
    "leaveDate": "2026-10-06"
  },
  {
    "name": "Louis Meng",
    "leaveDate": "2026-10-07"
  },
  {
    "name": "Louis Meng",
    "leaveDate": "2026-10-08"
  },
  {
    "name": "Louis Meng",
    "leaveDate": "2026-10-09"
  },
  {
    "name": "Mark Ma",
    "leaveDate": "2026-10-06"
  },
  {
    "name": "Mark Ma",
    "leaveDate": "2026-10-07"
  },
  {
    "name": "Monster Wang",
    "leaveDate": "2026-10-20"
  },
  {
    "name": "Peter Li",
    "leaveDate": "2026-10-06"
  },
  {
    "name": "Peter Li",
    "leaveDate": "2026-10-07"
  },
  {
    "name": "Rain Gu",
    "leaveDate": "2026-10-06"
  },
  {
    "name": "Rain Gu",
    "leaveDate": "2026-10-07"
  },
  {
    "name": "Reese Li",
    "leaveDate": "2026-10-30"
  },
  {
    "name": "Vae Wang",
    "leaveDate": "2026-10-06"
  },
  {
    "name": "Vae Wang",
    "leaveDate": "2026-10-07"
  },
  {
    "name": "DK Xiong",
    "leaveDate": "2026-11-04"
  },
  {
    "name": "Jim Hu",
    "leaveDate": "2026-11-12"
  },
  {
    "name": "Jim Hu",
    "leaveDate": "2026-11-13"
  },
  {
    "name": "Louis Meng",
    "leaveDate": "2026-11-12"
  },
  {
    "name": "Louis Meng",
    "leaveDate": "2026-11-13"
  },
  {
    "name": "Max Chen",
    "leaveDate": "2026-11-26"
  },
  {
    "name": "Max Chen",
    "leaveDate": "2026-11-27"
  },
  {
    "name": "Peter Li",
    "leaveDate": "2026-11-27"
  },
  {
    "name": "DK Xiong",
    "leaveDate": "2026-12-02"
  },
  {
    "name": "Dylan Xie",
    "leaveDate": "2026-12-24"
  },
  {
    "name": "Dylan Xie",
    "leaveDate": "2026-12-25"
  },
  {
    "name": "Dylan Xie",
    "leaveDate": "2026-12-31"
  },
  {
    "name": "Iron Xia",
    "leaveDate": "2026-12-31"
  },
  {
    "name": "Layne Wang",
    "leaveDate": "2026-12-15"
  },
  {
    "name": "Zick Ling",
    "leaveDate": "2026-12-23"
  },
  {
    "name": "Zick Ling",
    "leaveDate": "2026-12-24"
  },
  {
    "name": "Zick Ling",
    "leaveDate": "2026-12-25"
  },
  {
    "name": "Iris Li",
    "leaveDate": "2026-12-28"
  },
  {
    "name": "Iris Li",
    "leaveDate": "2026-12-29"
  },
  {
    "name": "Iris Li",
    "leaveDate": "2026-12-30"
  }
]